setup.py
testmania/__init__.py
testmania/deep.py
testmania/expect.py
testmania/pep8.py
testmania/time.py
testmania/xml.py
testmania.egg-info/PKG-INFO
testmania.egg-info/SOURCES.txt
testmania.egg-info/dependency_links.txt
testmania.egg-info/requires.txt
testmania.egg-info/top_level.txt