Metadata-Version: 1.0
Name: testmania
Version: 0.4.2
Summary: Library of assert_xxx functions for more convenient testing
Home-page: https://github.com/nailxx/testmania
Author: Victor Nakoryakov (aka nailxx)
Author-email: nail.xx@gmail.com
License: MIT
Keywords: test unittest assert
Platform: UNKNOWN
Classifier: Development Status :: 3 - Alpha
Classifier: License :: OSI Approved :: MIT License
Classifier: Intended Audience :: Developers
Classifier: Operating System :: OS Independent
Classifier: Programming Language :: Python
Classifier: Topic :: Software Development :: Testing
